LICENSE
README.md
setup.py
delapp_helper.egg-info/PKG-INFO
delapp_helper.egg-info/SOURCES.txt
delapp_helper.egg-info/dependency_links.txt
delapp_helper.egg-info/not-zip-safe
delapp_helper.egg-info/requires.txt
delapp_helper.egg-info/top_level.txt
delapphelper/__init__.py
delapphelper/delapphelper.py