Metadata-Version: 2.1
Name: delapp-helper
Version: 0.1.3
Summary: a small wrapper for the penny-del api
Home-page: https://github.com/grindsa/delapp_helper
Author: grindsa
Author-email: grindelsack@gmail.com
License: GPL
Platform: any
Classifier: Programming Language :: Python
Classifier: Development Status :: 4 - Beta
Classifier: Natural Language :: German
Classifier: Intended Audience :: Developers
Classifier: License :: OSI Approved :: GNU General Public License v3 or later (GPLv3+)
Classifier: Operating System :: OS Independent
Classifier: Topic :: Software Development :: Libraries :: Python Modules
License-File: LICENSE
